odoo/addons/shopinvader_api_payment_provider_stripe/README.rst
odoo/addons/shopinvader_api_payment_provider_stripe/__init__.py
odoo/addons/shopinvader_api_payment_provider_stripe/__manifest__.py
odoo/addons/shopinvader_api_payment_provider_stripe/i18n/shopinvader_api_payment_provider_stripe.pot
odoo/addons/shopinvader_api_payment_provider_stripe/models/__init__.py
odoo/addons/shopinvader_api_payment_provider_stripe/models/payment_transaction_stripe.py
odoo/addons/shopinvader_api_payment_provider_stripe/readme/CONTRIBUTORS.rst
odoo/addons/shopinvader_api_payment_provider_stripe/readme/USAGE.rst
odoo/addons/shopinvader_api_payment_provider_stripe/routers/__init__.py
odoo/addons/shopinvader_api_payment_provider_stripe/routers/payment_stripe.py
odoo/addons/shopinvader_api_payment_provider_stripe/schemas/__init__.py
odoo/addons/shopinvader_api_payment_provider_stripe/schemas/transaction_processing_values.py
odoo_addon_shopinvader_api_payment_provider_stripe-16.0.1.0.0.6.dist-info/METADATA
odoo_addon_shopinvader_api_payment_provider_stripe-16.0.1.0.0.6.dist-info/WHEEL
odoo_addon_shopinvader_api_payment_provider_stripe-16.0.1.0.0.6.dist-info/top_level.txt
odoo_addon_shopinvader_api_payment_provider_stripe-16.0.1.0.0.6.dist-info/RECORD
